<?xml version="1.0" encoding="EUC-KR" ?>

<protocol>



	
	
			<chartdata symbol="357780" name="솔브레인" count="1361" timeframe="day" precision="0" origintime="20200806">
			
				<item data="20200806|201600|262000|201600|262000|75906" />
			
				<item data="20200807|298200|328000|270000|282000|1828517" />
			
				<item data="20200810|261500|272000|235400|256900|377291" />
			
				<item data="20200811|261000|262700|240000|241000|255786" />
			
				<item data="20200812|238100|258800|225200|248000|409538" />
			
				<item data="20200813|249800|250800|243500|247800|111673" />
			
				<item data="20200814|245400|247800|235900|236100|108771" />
			
				<item data="20200818|229000|235000|213200|214000|172350" />
			
				<item data="20200819|214000|229700|214000|222400|139885" />
			
				<item data="20200820|218800|222300|206900|207500|113690" />
			
				<item data="20200821|214000|221400|206000|214300|112805" />
			
				<item data="20200824|213800|224000|207800|221000|89071" />
			
				<item data="20200825|225000|239300|218800|235600|148257" />
			
				<item data="20200826|235700|241000|229000|232000|102963" />
			
				<item data="20200827|230900|230900|220300|225000|144001" />
			
				<item data="20200828|227100|228000|215500|216900|106858" />
			
				<item data="20200831|218500|221900|216100|216800|63239" />
			
				<item data="20200901|216800|219000|209300|210300|95539" />
			
				<item data="20200902|212400|215200|209500|210100|85563" />
			
				<item data="20200903|212900|223500|211200|223000|125681" />
			
				<item data="20200904|212000|216700|211500|213200|110591" />
			
				<item data="20200907|215000|219500|211700|216500|79070" />
			
				<item data="20200908|219100|219100|212300|213100|59114" />
			
				<item data="20200909|208000|209800|206500|207000|67785" />
			
				<item data="20200910|210500|211900|206000|207700|66432" />
			
				<item data="20200911|207500|207500|201100|204700|88424" />
			
				<item data="20200914|206400|213400|204000|213400|76929" />
			
				<item data="20200915|220300|235300|220100|231500|368205" />
			
				<item data="20200916|236000|240500|227300|229800|158086" />
			
				<item data="20200917|231400|231800|222100|225000|75510" />
			
				<item data="20200918|224500|235000|220100|233100|83226" />
			
				<item data="20200921|232100|234700|223800|225300|65042" />
			
				<item data="20200922|223600|225000|215000|215400|77506" />
			
				<item data="20200923|219000|219600|209200|217000|65531" />
			
				<item data="20200924|209200|213800|208400|209300|50755" />
			
				<item data="20200925|211600|213800|207200|213000|31670" />
			
				<item data="20200928|215500|217400|213500|215900|31593" />
			
				<item data="20200929|216500|218000|214400|216700|37620" />
			
				<item data="20201005|216600|216600|212900|215200|26040" />
			
				<item data="20201006|216300|224100|215000|224000|70873" />
			
				<item data="20201007|221200|240800|220700|240000|231916" />
			
				<item data="20201008|240100|248000|234800|239700|143959" />
			
				<item data="20201012|241200|242100|236000|241800|77634" />
			
				<item data="20201013|249400|257000|243800|249700|229897" />
			
				<item data="20201014|250900|256600|240100|241500|126942" />
			
				<item data="20201015|244800|244800|232000|241300|83889" />
			
				<item data="20201016|240000|240600|230000|231200|66267" />
			
				<item data="20201019|227700|235700|225600|226100|57056" />
			
				<item data="20201020|222800|237100|222200|235800|74845" />
			
				<item data="20201021|235800|238500|234100|238100|36935" />
			
				<item data="20201022|238000|238000|229000|229200|54199" />
			
				<item data="20201023|230300|231500|225400|228700|43675" />
			
				<item data="20201026|226300|227700|214000|216000|80915" />
			
				<item data="20201027|215200|219000|210500|217700|54300" />
			
				<item data="20201028|220300|223900|214400|219800|57530" />
			
				<item data="20201029|214500|221200|214200|220300|30453" />
			
				<item data="20201030|221000|221700|215400|217400|35706" />
			
				<item data="20201102|215400|219600|214600|218200|22596" />
			
				<item data="20201103|221800|224500|220400|222100|37879" />
			
				<item data="20201104|224500|233800|222000|233000|63872" />
			
				<item data="20201105|233100|234900|229000|233600|49124" />
			
				<item data="20201106|235100|236400|231400|233600|36445" />
			
				<item data="20201109|235500|237800|234800|235500|39641" />
			
				<item data="20201110|235000|235000|227500|231300|57656" />
			
				<item data="20201111|231400|231400|223000|227100|74348" />
			
				<item data="20201112|227300|230600|227300|228000|40629" />
			
				<item data="20201113|229100|232900|228200|232000|39262" />
			
				<item data="20201116|234900|244900|234900|241000|107721" />
			
				<item data="20201117|242800|243100|235800|241800|67004" />
			
				<item data="20201118|241800|247000|240500|241700|61608" />
			
				<item data="20201119|240900|241000|237500|240000|49561" />
			
				<item data="20201120|241700|248000|241400|246400|92778" />
			
				<item data="20201123|247000|258000|247000|255900|124084" />
			
				<item data="20201124|259200|264100|250400|256900|115110" />
			
				<item data="20201125|258500|258500|244600|248000|156077" />
			
				<item data="20201126|249000|254000|245300|252700|78606" />
			
				<item data="20201127|253000|255000|253000|254800|50311" />
			
				<item data="20201130|255900|256800|251500|254300|61520" />
			
				<item data="20201201|254400|257700|250600|254900|47230" />
			
				<item data="20201202|256200|259600|255000|255400|58798" />
			
				<item data="20201203|257000|259000|252800|254100|66514" />
			
				<item data="20201204|255000|255200|251300|254500|69965" />
			
				<item data="20201207|256000|256700|251300|252600|54622" />
			
				<item data="20201208|252600|255100|251000|251500|48935" />
			
				<item data="20201209|250500|253300|250000|250200|53926" />
			
				<item data="20201210|249900|258000|247500|247500|176857" />
			
				<item data="20201211|248500|250000|247100|247700|71133" />
			
				<item data="20201214|247100|250800|245000|250700|43048" />
			
				<item data="20201215|253000|256000|250700|255000|68540" />
			
				<item data="20201216|256900|256900|251600|255100|64797" />
			
				<item data="20201217|255300|274000|254000|273800|227475" />
			
				<item data="20201218|280000|282500|271200|276600|127091" />
			
				<item data="20201221|275700|275700|267000|273700|71913" />
			
				<item data="20201222|270100|270100|259200|260000|119975" />
			
				<item data="20201223|262500|266300|256400|265500|65917" />
			
				<item data="20201224|268100|268900|263800|267600|41428" />
			
				<item data="20201228|267600|272000|265000|271400|75119" />
			
				<item data="20201229|271600|272500|265000|271200|52994" />
			
				<item data="20201230|271200|276600|268000|272300|73978" />
			
				<item data="20210104|275500|292300|270800|291400|155472" />
			
				<item data="20210105|291000|304800|285900|295000|144406" />
			
				<item data="20210106|295000|300500|288000|290000|111422" />
			
				<item data="20210107|290100|293200|288000|290600|76106" />
			
				<item data="20210108|291400|292800|285000|288600|102309" />
			
				<item data="20210111|289200|290000|276000|282800|111476" />
			
				<item data="20210112|280100|285000|275800|279700|56760" />
			
				<item data="20210113|279700|283400|279600|280400|44659" />
			
				<item data="20210114|280400|288700|280400|288700|45876" />
			
				<item data="20210115|288900|290000|278500|281900|63001" />
			
				<item data="20210118|275800|279000|269200|273500|69750" />
			
				<item data="20210119|272100|274000|268800|273600|54392" />
			
				<item data="20210120|274900|281200|273700|278600|58773" />
			
				<item data="20210121|281600|283100|276000|278600|46429" />
			
				<item data="20210122|282300|282300|273200|275300|49525" />
			
				<item data="20210125|279500|286900|277000|282000|77263" />
			
				<item data="20210126|287500|303900|283900|300000|262998" />
			
				<item data="20210127|301100|306700|286100|286100|134215" />
			
				<item data="20210128|280000|285900|277200|280100|67430" />
			
				<item data="20210129|281200|284500|264100|268700|86627" />
			
				<item data="20210201|269000|273900|265000|273400|41390" />
			
				<item data="20210202|275900|278900|269900|272000|49945" />
			
				<item data="20210203|273200|276000|268000|272000|37834" />
			
				<item data="20210204|272200|275000|266900|269000|41559" />
			
				<item data="20210205|273300|280600|272400|277000|79738" />
			
				<item data="20210208|283000|294600|281100|291400|155537" />
			
				<item data="20210209|291400|296200|287000|291800|71336" />
			
				<item data="20210210|297000|297000|286000|294900|61722" />
			
				<item data="20210215|297900|300400|294600|300000|78569" />
			
				<item data="20210216|302000|319600|301900|312500|157244" />
			
				<item data="20210217|312600|317800|305800|313600|67670" />
			
				<item data="20210218|315000|315700|302900|303000|90823" />
			
				<item data="20210219|312000|324000|304500|321900|148307" />
			
				<item data="20210222|321600|329700|313700|323600|85956" />
			
				<item data="20210223|314900|316900|304300|307000|106520" />
			
				<item data="20210224|310000|319900|305000|308300|123621" />
			
				<item data="20210225|318000|327000|307700|322800|129679" />
			
				<item data="20210226|310500|313800|306300|309800|85599" />
			
				<item data="20210302|318500|319000|306000|310000|43788" />
			
				<item data="20210303|308100|308100|303000|307100|37783" />
			
				<item data="20210304|302000|305000|297500|300600|55400" />
			
				<item data="20210305|295700|300000|290100|296100|36831" />
			
				<item data="20210308|303000|303000|293100|293800|22543" />
			
				<item data="20210309|290000|291000|281000|285700|51678" />
			
				<item data="20210310|294900|294900|285800|290800|31891" />
			
				<item data="20210311|291100|302300|288900|302300|48998" />
			
				<item data="20210312|303900|308400|303200|307300|31285" />
			
				<item data="20210315|308200|308200|301000|303000|20235" />
			
				<item data="20210316|306000|309100|303800|308900|23580" />
			
				<item data="20210317|309400|309700|299700|303500|30037" />
			
				<item data="20210318|305000|305500|300000|300000|30506" />
			
				<item data="20210319|295400|300000|294500|299700|28981" />
			
				<item data="20210322|300000|301600|295200|299900|20372" />
			
				<item data="20210323|300900|300900|295000|296200|20584" />
			
				<item data="20210324|294200|302600|290900|302100|29178" />
			
				<item data="20210325|300300|301200|295600|298500|23191" />
			
				<item data="20210326|300900|300900|293900|294100|26842" />
			
				<item data="20210329|294200|296500|289600|290800|32452" />
			
				<item data="20210330|289500|293200|289300|290700|21692" />
			
				<item data="20210331|290700|291800|289100|289700|22799" />
			
				<item data="20210401|289900|297600|289500|293500|37698" />
			
				<item data="20210402|299800|308900|296100|308800|90464" />
			
				<item data="20210405|308800|312100|306200|310700|32951" />
			
				<item data="20210406|309600|312000|303400|305800|29874" />
			
				<item data="20210407|307200|307300|302000|303200|20997" />
			
				<item data="20210408|300500|304900|300400|300800|23752" />
			
				<item data="20210409|300800|309400|300800|305800|44688" />
			
				<item data="20210412|307000|307600|302000|302300|37838" />
			
				<item data="20210413|302400|311800|302300|309200|45214" />
			
				<item data="20210414|309000|311400|305700|307900|31512" />
			
				<item data="20210415|308000|310900|306200|309700|31376" />
			
				<item data="20210416|311300|318500|310100|315800|40948" />
			
				<item data="20210419|316200|330000|314500|329300|96696" />
			
				<item data="20210420|327400|327500|323000|324700|40145" />
			
				<item data="20210421|324400|324500|319000|320500|44646" />
			
				<item data="20210422|324000|344000|323500|336100|105121" />
			
				<item data="20210423|336200|348500|332600|336600|77018" />
			
				<item data="20210426|342000|361600|340000|356700|91686" />
			
				<item data="20210427|358500|360000|350000|351000|42032" />
			
				<item data="20210428|350600|352700|340000|342300|60302" />
			
				<item data="20210429|342300|354000|341700|350000|41263" />
			
				<item data="20210430|351400|359700|349900|355800|50000" />
			
				<item data="20210503|357400|357400|346000|350000|58047" />
			
				<item data="20210504|347500|350000|342700|348900|35285" />
			
				<item data="20210506|348000|354300|342800|354300|27553" />
			
				<item data="20210507|355100|356500|349700|350700|22746" />
			
				<item data="20210510|350700|352500|349800|351000|19538" />
			
				<item data="20210511|349100|349100|340000|340500|49858" />
			
				<item data="20210512|344000|344000|333000|340200|29433" />
			
				<item data="20210513|330000|335400|324000|327900|57410" />
			
				<item data="20210514|330000|334200|328000|334200|24335" />
			
				<item data="20210517|336200|336500|327000|332000|19182" />
			
				<item data="20210518|332100|333600|327100|331000|40614" />
			
				<item data="20210520|331500|341400|331000|339000|26840" />
			
				<item data="20210521|344000|344000|333000|338200|33977" />
			
				<item data="20210524|335600|338300|326800|328000|33232" />
			
				<item data="20210525|329100|330400|324100|325100|39321" />
			
				<item data="20210526|326900|326900|323900|325500|28558" />
			
				<item data="20210527|325600|328300|323600|327000|24920" />
			
				<item data="20210528|327100|330000|326800|328100|16428" />
			
				<item data="20210531|328400|329500|327300|328200|17289" />
			
				<item data="20210601|328000|330100|328000|328300|13540" />
			
				<item data="20210602|329000|329800|325500|327800|29091" />
			
				<item data="20210603|329000|349200|328000|344600|58988" />
			
				<item data="20210604|344000|347500|338800|344000|23054" />
			
				<item data="20210607|345500|349900|341600|344000|17154" />
			
				<item data="20210608|344100|345900|333800|333800|25874" />
			
				<item data="20210609|335000|335000|325000|327000|47755" />
			
				<item data="20210610|327000|331800|326000|330000|33416" />
			
				<item data="20210611|332300|332600|328000|329100|15898" />
			
				<item data="20210614|330100|331300|326000|328000|16899" />
			
				<item data="20210615|330500|330500|327000|328500|22674" />
			
				<item data="20210616|328500|329300|325500|327500|14349" />
			
				<item data="20210617|326100|331700|325600|331200|25931" />
			
				<item data="20210618|334000|334000|328300|330200|22940" />
			
				<item data="20210621|328100|335700|326000|327100|17257" />
			
				<item data="20210622|328300|329700|326400|328500|17591" />
			
				<item data="20210623|330500|330500|325000|325500|27867" />
			
				<item data="20210624|325600|327100|320400|321600|34461" />
			
				<item data="20210625|322000|326000|321100|321800|23835" />
			
				<item data="20210628|323700|327700|321800|326900|24118" />
			
				<item data="20210629|327100|330700|325600|328600|23536" />
			
				<item data="20210630|328600|331300|326400|328700|15919" />
			
				<item data="20210701|329100|330200|325600|325800|30160" />
			
				<item data="20210702|325800|326800|320800|320900|61347" />
			
				<item data="20210705|321000|323000|318600|318600|30716" />
			
				<item data="20210706|318800|322600|318600|322100|19852" />
			
				<item data="20210707|322100|323600|319000|320600|37665" />
			
				<item data="20210708|320800|321300|314200|317600|42907" />
			
				<item data="20210709|315000|324000|313400|316500|47660" />
			
				<item data="20210712|316500|320000|314300|317000|20800" />
			
				<item data="20210713|317100|317100|303900|308100|91683" />
			
				<item data="20210714|308100|311400|305000|311000|41455" />
			
				<item data="20210715|310100|323600|308400|319400|54190" />
			
				<item data="20210716|318900|328200|315300|327800|46492" />
			
				<item data="20210719|327500|343000|324700|337700|79001" />
			
				<item data="20210720|334300|353000|332100|351000|98911" />
			
				<item data="20210721|350000|351200|342000|348700|46149" />
			
				<item data="20210722|346200|369800|346100|367700|82259" />
			
				<item data="20210723|364600|372600|352000|353500|67603" />
			
				<item data="20210726|354500|356500|345300|350400|42094" />
			
				<item data="20210727|346500|352800|346500|348000|18238" />
			
				<item data="20210728|345000|352500|340700|342000|27117" />
			
				<item data="20210729|343300|344600|339000|343700|14633" />
			
				<item data="20210730|343100|343100|336800|339800|21672" />
			
				<item data="20210802|337700|341300|334700|340800|15726" />
			
				<item data="20210803|340500|348300|337500|346300|30843" />
			
				<item data="20210804|347000|347000|340500|341500|22555" />
			
				<item data="20210805|343000|343300|338500|340000|15582" />
			
				<item data="20210806|340500|340500|335000|336200|19395" />
			
				<item data="20210809|333100|340500|333000|338200|31760" />
			
				<item data="20210810|340400|340500|336200|339500|16480" />
			
				<item data="20210811|339600|345700|325100|327800|46252" />
			
				<item data="20210812|328900|334000|324000|329000|34725" />
			
				<item data="20210813|329100|329500|306200|324200|41877" />
			
				<item data="20210817|322000|322000|310000|312000|44327" />
			
				<item data="20210818|307600|308500|293000|299500|92636" />
			
				<item data="20210819|298600|298600|288000|288000|60648" />
			
				<item data="20210820|288000|293700|276200|277400|69219" />
			
				<item data="20210823|281700|283900|278500|282600|42111" />
			
				<item data="20210824|285200|285900|276300|280700|70684" />
			
				<item data="20210825|284500|286800|274400|276300|89210" />
			
				<item data="20210826|277000|281800|273400|275800|103574" />
			
				<item data="20210827|275800|294500|275000|289000|99503" />
			
				<item data="20210830|295100|295500|281200|284100|62177" />
			
				<item data="20210831|284300|285100|281800|283300|34512" />
			
				<item data="20210901|284800|291500|282000|291200|63533" />
			
				<item data="20210902|291200|292000|286500|291000|36974" />
			
				<item data="20210903|290900|292000|286100|287900|43501" />
			
				<item data="20210906|287900|287900|282600|286100|47223" />
			
				<item data="20210907|286100|291000|286100|286800|29479" />
			
				<item data="20210908|287000|287300|281100|281100|34468" />
			
				<item data="20210909|279500|281100|274100|278700|47213" />
			
				<item data="20210910|278700|281800|274100|281700|43965" />
			
				<item data="20210913|281700|281700|276000|278300|56234" />
			
				<item data="20210914|278900|286600|278300|285000|43241" />
			
				<item data="20210915|283600|303500|283600|302700|113059" />
			
				<item data="20210916|303000|303200|294500|294700|58985" />
			
				<item data="20210917|295300|298900|290000|296900|47766" />
			
				<item data="20210923|296100|303800|288000|290100|55591" />
			
				<item data="20210924|292100|292700|286500|291000|41792" />
			
				<item data="20210927|290700|293000|282000|291000|58336" />
			
				<item data="20210928|289500|290900|282100|282300|31889" />
			
				<item data="20210929|274100|277000|267700|271900|69081" />
			
				<item data="20210930|271900|273900|269600|273200|40385" />
			
				<item data="20211001|272000|272100|264500|265700|42217" />
			
				<item data="20211005|259400|261200|252800|259000|47483" />
			
				<item data="20211006|259000|261900|250000|250000|45991" />
			
				<item data="20211007|255900|259600|253400|257900|19265" />
			
				<item data="20211008|259000|259000|250000|251700|38003" />
			
				<item data="20211012|251000|251100|240900|244500|39466" />
			
				<item data="20211013|244500|247900|243000|243600|43725" />
			
				<item data="20211014|243600|250200|242400|247600|42316" />
			
				<item data="20211015|251300|265500|251300|263100|64280" />
			
				<item data="20211018|266400|267400|261000|262700|31404" />
			
				<item data="20211019|262900|263700|259400|262200|26876" />
			
				<item data="20211020|263800|266000|259800|260700|22531" />
			
				<item data="20211021|259900|261400|256000|257100|30135" />
			
				<item data="20211022|258400|258400|254200|255000|18191" />
			
				<item data="20211025|253000|256900|251000|253300|16703" />
			
				<item data="20211026|255400|263000|255100|259200|22738" />
			
				<item data="20211027|257300|264900|257200|264200|36754" />
			
				<item data="20211028|263000|269500|261200|263800|32857" />
			
				<item data="20211029|265200|271400|260900|261600|35688" />
			
				<item data="20211101|261600|264000|260600|261600|15578" />
			
				<item data="20211102|261700|263900|257300|258600|20422" />
			
				<item data="20211103|262300|262300|252000|253700|23018" />
			
				<item data="20211104|252700|257600|249200|249600|33439" />
			
				<item data="20211105|250300|252000|246000|247800|23969" />
			
				<item data="20211108|248000|248100|241300|244300|28826" />
			
				<item data="20211109|244700|247200|239900|240900|28540" />
			
				<item data="20211110|240100|240900|231100|232100|40641" />
			
				<item data="20211111|232100|234200|229700|233200|29746" />
			
				<item data="20211112|234600|243400|228900|241900|47212" />
			
				<item data="20211115|242600|248500|240300|247700|39825" />
			
				<item data="20211116|248500|251600|247000|248500|33183" />
			
				<item data="20211117|250000|251000|240700|240900|30388" />
			
				<item data="20211118|240900|241000|230000|234400|52717" />
			
				<item data="20211119|230500|248500|230500|248100|69645" />
			
				<item data="20211122|253000|286000|253000|281000|233521" />
			
				<item data="20211123|281000|281100|270300|272800|54117" />
			
				<item data="20211124|273000|281600|266500|273800|52230" />
			
				<item data="20211125|283000|289000|273900|282500|105481" />
			
				<item data="20211126|285500|286500|271800|276500|57913" />
			
				<item data="20211129|265500|275000|264100|266300|40796" />
			
				<item data="20211130|271500|275300|253500|255800|39815" />
			
				<item data="20211201|255800|266900|253200|264200|37145" />
			
				<item data="20211202|263600|278800|261100|274700|56269" />
			
				<item data="20211203|272000|278000|269000|275900|23840" />
			
				<item data="20211206|275900|280900|274000|278000|27119" />
			
				<item data="20211207|279900|281600|277000|279500|21536" />
			
				<item data="20211208|282400|286800|282400|282500|42577" />
			
				<item data="20211209|282500|289500|282100|288300|42293" />
			
				<item data="20211210|288000|288000|276400|277200|32767" />
			
				<item data="20211213|277200|281600|276500|277700|21701" />
			
				<item data="20211214|276300|279800|276000|279700|18558" />
			
				<item data="20211215|276200|278200|273500|276100|25164" />
			
				<item data="20211216|279000|284300|277500|277700|13255" />
			
				<item data="20211217|273000|278000|272100|275900|15252" />
			
				<item data="20211220|275400|279400|272100|273800|12716" />
			
				<item data="20211221|274000|281200|272200|278600|21118" />
			
				<item data="20211222|282300|284900|277400|277700|16576" />
			
				<item data="20211223|277600|279500|276600|277500|64675" />
			
				<item data="20211224|279700|280000|272500|278900|23987" />
			
				<item data="20211227|277000|282000|276700|281900|22302" />
			
				<item data="20211228|284100|296000|284100|294700|66098" />
			
				<item data="20211229|293900|294000|283700|284600|37714" />
			
				<item data="20211230|283900|284200|274000|278500|47744" />
			
				<item data="20220103|279200|280200|274200|278000|20368" />
			
				<item data="20220104|278900|278900|271800|273400|22552" />
			
				<item data="20220105|273400|275000|260100|260800|47582" />
			
				<item data="20220106|259100|263400|254500|260000|34880" />
			
				<item data="20220107|261500|264900|256100|262000|30381" />
			
				<item data="20220110|262100|263000|256300|259500|24075" />
			
				<item data="20220111|260100|261400|254700|259000|25950" />
			
				<item data="20220112|259000|263300|255700|260100|41478" />
			
				<item data="20220113|260600|261500|256000|257800|34090" />
			
				<item data="20220114|257100|257200|253000|253700|24739" />
			
				<item data="20220117|254700|254700|248700|252600|29548" />
			
				<item data="20220118|253000|254000|246400|247900|21760" />
			
				<item data="20220119|244000|246900|239000|242000|39458" />
			
				<item data="20220120|242100|257900|239100|257000|40426" />
			
				<item data="20220121|252800|256400|249700|253000|26048" />
			
				<item data="20220124|252000|255700|250000|253300|29620" />
			
				<item data="20220125|254000|255300|242400|246100|37440" />
			
				<item data="20220126|248000|250700|243900|250700|21669" />
			
				<item data="20220127|250800|251300|239800|242800|33525" />
			
				<item data="20220128|242800|247000|238500|245000|41162" />
			
				<item data="20220203|245200|247500|238500|240500|44878" />
			
				<item data="20220204|239800|240700|236900|240400|34432" />
			
				<item data="20220207|240600|242800|231400|232400|36150" />
			
				<item data="20220208|233100|237800|231600|234100|27910" />
			
				<item data="20220209|234500|238800|231700|238800|58636" />
			
				<item data="20220210|240200|241500|235300|239200|33200" />
			
				<item data="20220211|234700|239500|233300|233500|21129" />
			
				<item data="20220214|230200|231500|222000|223000|35603" />
			
				<item data="20220215|223000|226400|221100|223300|15514" />
			
				<item data="20220216|227100|233000|225100|233000|22628" />
			
				<item data="20220217|233000|239200|228000|232200|33212" />
			
				<item data="20220218|228100|235000|227000|235000|16062" />
			
				<item data="20220221|234900|238200|226000|231900|14022" />
			
				<item data="20220222|228600|228800|225200|227300|13334" />
			
				<item data="20220223|226100|230600|225900|230600|13497" />
			
				<item data="20220224|226800|228900|225300|226600|18845" />
			
				<item data="20220225|230000|233800|226000|228300|17350" />
			
				<item data="20220228|227100|229400|222400|227300|23822" />
			
				<item data="20220302|226600|229000|224800|227500|12944" />
			
				<item data="20220303|228700|229600|227000|229500|29173" />
			
				<item data="20220304|228600|228600|222600|222700|32313" />
			
				<item data="20220307|221400|221400|212000|212300|39358" />
			
				<item data="20220308|211300|211300|206000|206000|32471" />
			
				<item data="20220310|210200|222300|209800|218400|68810" />
			
				<item data="20220311|216400|218000|214000|215600|18270" />
			
				<item data="20220314|215600|217200|207700|207700|19170" />
			
				<item data="20220315|205300|214000|205300|212300|20105" />
			
				<item data="20220316|216200|222000|216200|221700|27065" />
			
				<item data="20220317|227800|237900|227800|233500|63043" />
			
				<item data="20220318|235500|236200|231500|236100|23143" />
			
				<item data="20220321|236100|237900|230700|231800|27087" />
			
				<item data="20220322|231900|234500|229300|233800|22084" />
			
				<item data="20220323|235500|236700|230200|232500|16795" />
			
				<item data="20220324|232600|237600|231800|236700|26154" />
			
				<item data="20220325|240000|245500|238300|243200|47019" />
			
				<item data="20220328|245500|245800|239900|241500|22621" />
			
				<item data="20220329|242000|245900|241000|244400|13403" />
			
				<item data="20220330|246800|247800|243100|243800|16847" />
			
				<item data="20220331|244800|248600|244000|244800|15305" />
			
				<item data="20220401|243500|243500|235400|238900|23141" />
			
				<item data="20220404|238800|242300|235000|241600|12208" />
			
				<item data="20220405|242000|246200|239700|240000|14226" />
			
				<item data="20220406|237000|237100|234100|234300|15578" />
			
				<item data="20220407|233900|237800|231000|236400|15342" />
			
				<item data="20220408|236400|238100|233000|237300|17320" />
			
				<item data="20220411|237300|237400|232800|233100|9982" />
			
				<item data="20220412|229000|234800|228800|233900|12022" />
			
				<item data="20220413|234700|239500|232800|238300|16822" />
			
				<item data="20220414|239300|239600|236200|236400|15702" />
			
				<item data="20220415|234000|235500|231100|233300|16578" />
			
				<item data="20220418|232100|236000|231700|234700|8110" />
			
				<item data="20220419|234700|247400|234000|246800|42810" />
			
				<item data="20220420|247200|247200|240600|241600|20147" />
			
				<item data="20220421|241500|244100|241100|241300|13422" />
			
				<item data="20220422|239200|245000|235600|239500|22472" />
			
				<item data="20220425|235800|242000|232800|237100|15300" />
			
				<item data="20220426|237500|246700|237200|242600|24569" />
			
				<item data="20220427|232100|243400|232100|241300|18741" />
			
				<item data="20220428|242000|246300|242000|245100|17860" />
			
				<item data="20220429|246600|247500|244000|246000|15566" />
			
				<item data="20220502|245500|245500|240900|244800|10382" />
			
				<item data="20220503|243000|246500|242500|245100|11374" />
			
				<item data="20220504|245000|246500|242700|243300|10159" />
			
				<item data="20220506|241000|242900|235000|237000|14965" />
			
				<item data="20220509|237100|237800|233000|233300|9357" />
			
				<item data="20220510|230600|234100|223700|232700|17767" />
			
				<item data="20220511|230500|241500|225600|241200|19422" />
			
				<item data="20220512|237000|240400|233500|233500|20575" />
			
				<item data="20220513|236600|243500|234000|240100|21957" />
			
				<item data="20220516|242100|244800|236200|236900|12714" />
			
				<item data="20220517|244800|268800|241600|267400|134479" />
			
				<item data="20220518|267400|269600|263300|265600|41546" />
			
				<item data="20220519|260200|263900|256500|261400|48035" />
			
				<item data="20220520|260700|268100|260700|262800|42057" />
			
				<item data="20220523|269800|278800|269100|269900|83003" />
			
				<item data="20220524|271400|273300|260400|260600|40342" />
			
				<item data="20220525|263300|266800|258400|260600|27665" />
			
				<item data="20220526|266700|276800|266500|270900|70362" />
			
				<item data="20220527|276000|278600|270000|271800|30363" />
			
				<item data="20220530|275200|277400|268600|272000|23865" />
			
				<item data="20220531|270100|274000|269000|274000|26339" />
			
				<item data="20220602|270000|272400|267000|267700|16080" />
			
				<item data="20220603|268900|272700|265100|267600|16861" />
			
				<item data="20220607|265000|265000|258100|261200|23724" />
			
				<item data="20220608|261500|263200|259500|260900|19197" />
			
				<item data="20220609|265300|270500|262700|270500|38056" />
			
				<item data="20220610|269500|269600|264400|264400|15176" />
			
				<item data="20220613|254700|260900|254600|255600|26504" />
			
				<item data="20220614|250000|262000|250000|258500|29422" />
			
				<item data="20220615|257600|260100|253400|254600|19124" />
			
				<item data="20220616|259300|264800|254000|254900|21175" />
			
				<item data="20220617|250100|251900|242300|250600|29543" />
			
				<item data="20220620|252900|252900|242000|244600|17341" />
			
				<item data="20220621|245900|246700|236700|244200|30504" />
			
				<item data="20220622|247000|248600|225900|226100|34904" />
			
				<item data="20220623|226100|233800|218700|225800|24910" />
			
				<item data="20220624|227900|234100|227900|234100|16333" />
			
				<item data="20220627|237000|242900|228300|239800|18252" />
			
				<item data="20220628|237400|241800|236500|238600|12581" />
			
				<item data="20220629|235200|242000|234700|235300|18403" />
			
				<item data="20220630|237400|237400|226400|228600|21523" />
			
				<item data="20220701|228200|231200|216600|217500|26264" />
			
				<item data="20220704|216300|218500|208000|214200|32044" />
			
				<item data="20220705|214400|228000|214200|227200|27580" />
			
				<item data="20220706|225000|234300|221100|222300|25723" />
			
				<item data="20220707|222400|232500|222400|230000|19117" />
			
				<item data="20220708|232300|235000|228600|229600|16417" />
			
				<item data="20220711|229600|231200|226000|229000|14127" />
			
				<item data="20220712|225100|228300|212800|214400|39791" />
			
				<item data="20220713|214300|216800|211000|215300|22347" />
			
				<item data="20220714|214200|217600|211500|216900|23627" />
			
				<item data="20220715|218100|220600|213000|217500|17257" />
			
				<item data="20220718|220000|225000|217900|223700|19226" />
			
				<item data="20220719|218000|222800|218000|221600|9845" />
			
				<item data="20220720|226000|227300|223100|224800|19037" />
			
				<item data="20220721|226000|226100|223400|225900|15001" />
			
				<item data="20220722|226400|227800|223600|224100|17397" />
			
				<item data="20220725|222400|224500|220100|222800|13874" />
			
				<item data="20220726|228000|232300|226400|232200|28247" />
			
				<item data="20220727|232000|236000|230500|235800|15466" />
			
				<item data="20220728|237100|240900|231500|234200|22527" />
			
				<item data="20220729|234900|238500|232100|233100|15578" />
			
				<item data="20220801|234400|235200|231700|234000|11293" />
			
				<item data="20220802|234000|235500|230500|233700|11771" />
			
				<item data="20220803|233600|233600|231200|232700|17844" />
			
				<item data="20220804|233700|236600|230200|231300|17624" />
			
				<item data="20220805|231500|233900|231300|233600|12885" />
			
				<item data="20220808|233600|233600|229100|231700|14234" />
			
				<item data="20220809|231100|232300|222200|222800|37878" />
			
				<item data="20220810|220800|221100|218000|220800|35388" />
			
				<item data="20220811|223700|226500|223600|225200|20353" />
			
				<item data="20220812|224200|228700|223000|228300|15867" />
			
				<item data="20220816|230100|236800|229300|235100|33923" />
			
				<item data="20220817|232000|233600|225900|226500|42402" />
			
				<item data="20220818|224700|224700|219500|223200|33402" />
			
				<item data="20220819|224000|226000|220300|220300|20783" />
			
				<item data="20220822|217900|218000|213700|214100|28678" />
			
				<item data="20220823|211000|214100|210900|211000|19593" />
			
				<item data="20220824|212000|213900|209600|213600|17013" />
			
				<item data="20220825|213600|218500|212600|218200|25070" />
			
				<item data="20220826|219100|220500|215300|216500|18725" />
			
				<item data="20220829|210000|212100|206600|208500|39665" />
			
				<item data="20220830|210600|216700|209000|216400|27023" />
			
				<item data="20220831|212000|218000|211500|216800|13744" />
			
				<item data="20220901|212500|216900|211600|213400|19034" />
			
				<item data="20220902|213800|214400|209000|209300|16838" />
			
				<item data="20220905|209700|209900|206000|207300|15041" />
			
				<item data="20220906|208800|210400|206500|209100|14193" />
			
				<item data="20220907|209000|209100|205300|206100|15281" />
			
				<item data="20220908|207700|209800|206500|208500|16954" />
			
				<item data="20220913|213000|213500|210500|213500|15618" />
			
				<item data="20220914|205500|208100|205100|206200|14944" />
			
				<item data="20220915|207600|208400|206300|206300|6881" />
			
				<item data="20220916|205000|205100|202400|203700|16231" />
			
				<item data="20220919|203500|206100|201700|203500|16701" />
			
				<item data="20220920|203600|205200|194300|197500|38106" />
			
				<item data="20220921|196400|196400|189300|192500|39975" />
			
				<item data="20220922|188000|193100|186800|192400|16467" />
			
				<item data="20220923|192100|192100|188700|189800|12606" />
			
				<item data="20220926|188200|189000|182000|182500|26551" />
			
				<item data="20220927|181500|185400|180300|185400|25853" />
			
				<item data="20220928|182700|187800|182700|183700|21610" />
			
				<item data="20220929|187300|187500|179300|179400|20571" />
			
				<item data="20220930|176700|182000|176200|177900|22077" />
			
				<item data="20221004|179800|187200|179800|187200|22800" />
			
				<item data="20221005|189100|192400|188500|190200|28415" />
			
				<item data="20221006|192600|203400|191300|201800|28613" />
			
				<item data="20221007|199700|203900|197100|199500|16349" />
			
				<item data="20221011|195200|200200|193200|200200|19137" />
			
				<item data="20221012|197000|204200|197000|203800|21420" />
			
				<item data="20221013|200500|204300|200200|201400|24718" />
			
				<item data="20221014|204600|209900|203800|209500|31433" />
			
				<item data="20221017|207400|208900|205400|208000|12885" />
			
				<item data="20221018|212500|213500|209500|212500|17898" />
			
				<item data="20221019|210500|213400|209900|212000|17063" />
			
				<item data="20221020|210200|211400|207700|208900|23515" />
			
				<item data="20221021|205500|208100|202800|203400|13934" />
			
				<item data="20221024|206000|213400|206000|210900|18121" />
			
				<item data="20221025|210100|214000|209300|210500|15460" />
			
				<item data="20221026|210500|212900|207700|212000|10890" />
			
				<item data="20221027|212000|212500|206500|207000|13854" />
			
				<item data="20221028|204500|206600|200000|202000|20133" />
			
				<item data="20221031|202100|206600|201000|204700|12427" />
			
				<item data="20221101|204900|209300|204600|209200|17288" />
			
				<item data="20221102|207600|208700|203500|204000|16534" />
			
				<item data="20221103|200000|205100|199400|203500|14709" />
			
				<item data="20221104|201300|204700|200600|202200|11537" />
			
				<item data="20221107|202600|206900|202600|206900|11680" />
			
				<item data="20221108|207100|219000|207100|216500|25849" />
			
				<item data="20221109|215200|219200|215100|215600|20130" />
			
				<item data="20221110|214000|215900|211200|212900|13924" />
			
				<item data="20221111|224900|225400|217500|221000|29236" />
			
				<item data="20221114|221000|221000|214100|214200|17379" />
			
				<item data="20221115|213800|219100|213400|219100|14538" />
			
				<item data="20221116|222200|228400|219000|223000|33553" />
			
				<item data="20221117|224800|224800|218100|218700|13178" />
			
				<item data="20221118|218200|222500|213800|213900|15695" />
			
				<item data="20221121|213600|215600|209000|211500|11996" />
			
				<item data="20221122|211300|213000|206900|210700|10682" />
			
				<item data="20221123|211300|219600|211300|219200|12063" />
			
				<item data="20221124|217100|221200|217100|219900|6817" />
			
				<item data="20221125|217500|220400|216000|217500|4483" />
			
				<item data="20221128|213300|215000|211000|213300|11402" />
			
				<item data="20221129|213300|216400|211500|215300|6920" />
			
				<item data="20221130|215000|215000|211600|213100|13485" />
			
				<item data="20221201|216100|225500|216100|220400|33015" />
			
				<item data="20221202|224700|225700|217100|217100|13183" />
			
				<item data="20221205|217100|224400|217100|222200|12391" />
			
				<item data="20221206|221500|223000|212500|216400|7317" />
			
				<item data="20221207|214800|216000|212400|212600|7562" />
			
				<item data="20221208|210000|220000|210000|216900|22684" />
			
				<item data="20221209|217500|224900|217500|222900|17582" />
			
				<item data="20221212|220900|220900|214600|215400|10311" />
			
				<item data="20221213|215500|224800|214500|222100|12074" />
			
				<item data="20221214|221500|233400|220500|229000|37179" />
			
				<item data="20221215|227500|228700|223200|225000|15471" />
			
				<item data="20221216|222000|222000|218000|218300|9064" />
			
				<item data="20221219|218300|222500|215200|222000|7136" />
			
				<item data="20221220|220000|220400|215700|216600|7672" />
			
				<item data="20221221|219300|219700|215000|216700|11271" />
			
				<item data="20221222|218900|222800|217000|221400|11278" />
			
				<item data="20221223|216700|218800|215300|216700|7443" />
			
				<item data="20221226|215000|227900|213700|227600|15288" />
			
				<item data="20221227|229900|230000|225100|229900|17430" />
			
				<item data="20221228|227700|227700|218500|221100|18508" />
			
				<item data="20221229|218900|220300|214400|217900|10132" />
			
				<item data="20230102|217900|220900|214800|216300|8070" />
			
				<item data="20230103|212600|217400|212600|215200|9360" />
			
				<item data="20230104|214400|229500|212800|228300|18498" />
			
				<item data="20230105|230000|230800|223000|225700|14564" />
			
				<item data="20230106|224000|229000|222600|228500|12580" />
			
				<item data="20230109|229500|236000|229300|231400|10215" />
			
				<item data="20230110|231500|233000|228000|228500|11579" />
			
				<item data="20230111|229900|237000|228600|234400|21472" />
			
				<item data="20230112|237000|237400|229900|232000|13913" />
			
				<item data="20230113|233500|234600|229000|231800|7943" />
			
				<item data="20230116|233500|234400|230000|231400|5177" />
			
				<item data="20230117|230600|230700|226300|226700|8482" />
			
				<item data="20230118|226700|228000|224600|226300|6868" />
			
				<item data="20230119|225000|226800|223000|225800|7089" />
			
				<item data="20230120|225700|229500|223300|224900|7273" />
			
				<item data="20230125|228500|235000|228500|234500|11585" />
			
				<item data="20230126|234000|235500|229000|235500|10124" />
			
				<item data="20230127|238000|238500|231500|232500|7798" />
			
				<item data="20230130|230500|235000|229000|232500|9137" />
			
				<item data="20230131|232500|235500|228500|233500|12659" />
			
				<item data="20230201|234000|238000|232500|235500|9323" />
			
				<item data="20230202|239000|246500|239000|242000|25844" />
			
				<item data="20230203|242000|242000|235000|235500|10789" />
			
				<item data="20230206|234500|235000|230000|232000|13264" />
			
				<item data="20230207|234500|237500|231500|236500|10018" />
			
				<item data="20230208|237000|242000|235500|240000|10170" />
			
				<item data="20230209|237000|246500|237000|244500|18601" />
			
				<item data="20230210|241000|246000|234500|237500|16888" />
			
				<item data="20230213|234000|237500|232000|235000|11974" />
			
				<item data="20230214|239500|244000|236500|243500|16205" />
			
				<item data="20230215|243500|245500|233500|235000|21070" />
			
				<item data="20230216|237500|248000|237500|246000|24492" />
			
				<item data="20230217|240500|243500|236500|238000|15845" />
			
				<item data="20230220|238000|244000|232500|244000|14362" />
			
				<item data="20230221|241500|242000|238500|241500|14495" />
			
				<item data="20230222|238500|239500|231500|233500|24899" />
			
				<item data="20230223|234500|237500|232500|236000|13938" />
			
				<item data="20230224|238000|238000|228500|232000|18465" />
			
				<item data="20230227|230000|230500|225500|229000|8825" />
			
				<item data="20230228|229500|236500|229500|234000|17580" />
			
				<item data="20230302|234000|236500|229500|230000|18101" />
			
				<item data="20230303|232000|236000|231000|234000|20691" />
			
				<item data="20230306|237500|237500|227500|234500|38602" />
			
				<item data="20230307|235500|240000|229500|231500|29459" />
			
				<item data="20230308|229000|231000|223500|224500|32180" />
			
				<item data="20230309|228500|231500|224000|231500|16520" />
			
				<item data="20230310|227000|228000|224000|226500|16465" />
			
				<item data="20230313|225500|231000|223000|228500|13211" />
			
				<item data="20230314|224500|227500|212500|213000|24007" />
			
				<item data="20230315|220000|220000|215000|218500|13300" />
			
				<item data="20230316|218000|219500|213500|215000|34751" />
			
				<item data="20230317|220500|225500|220000|225500|35190" />
			
				<item data="20230320|225500|226500|214000|216000|27116" />
			
				<item data="20230321|217500|218000|209500|209500|31971" />
			
				<item data="20230322|212000|213000|205500|210000|28692" />
			
				<item data="20230323|205000|210000|203000|207000|30696" />
			
				<item data="20230324|209000|215500|205500|212500|29523" />
			
				<item data="20230327|215000|215500|207000|210500|20454" />
			
				<item data="20230328|209500|216500|208000|216000|24716" />
			
				<item data="20230329|218000|218500|214000|217500|22143" />
			
				<item data="20230330|223000|236500|222500|236000|70994" />
			
				<item data="20230331|236000|239000|230000|235000|28261" />
			
				<item data="20230403|235500|235500|229000|231500|25887" />
			
				<item data="20230404|231500|231500|223500|225000|35911" />
			
				<item data="20230405|224500|228500|223000|228000|23275" />
			
				<item data="20230406|225500|225500|218500|220000|33278" />
			
				<item data="20230407|221500|237000|221500|234000|51408" />
			
				<item data="20230410|234000|237000|229500|234000|31963" />
			
				<item data="20230411|235500|241000|233000|235000|31719" />
			
				<item data="20230412|235500|238500|231000|234500|31890" />
			
				<item data="20230413|234000|237000|227000|231000|19662" />
			
				<item data="20230414|231000|233500|226000|230000|20905" />
			
				<item data="20230417|234000|234000|227000|231500|23272" />
			
				<item data="20230418|229500|230000|224500|227500|25543" />
			
				<item data="20230419|227500|230000|223500|225000|16017" />
			
				<item data="20230420|225500|227000|220000|221500|22520" />
			
				<item data="20230421|219500|224000|217500|220000|12862" />
			
				<item data="20230424|223000|223000|214000|216500|21215" />
			
				<item data="20230425|215000|218000|211000|214000|14329" />
			
				<item data="20230426|214000|215000|209000|210500|19763" />
			
				<item data="20230427|211000|219000|207000|218500|20765" />
			
				<item data="20230428|218500|220500|214000|219000|25040" />
			
				<item data="20230502|219000|219000|214500|218000|12406" />
			
				<item data="20230503|215000|220000|213500|218500|16201" />
			
				<item data="20230504|219500|220000|215500|219500|10180" />
			
				<item data="20230508|219500|225000|217500|225000|34521" />
			
				<item data="20230509|222000|223000|216000|220000|19742" />
			
				<item data="20230510|220500|220500|212500|213500|16366" />
			
				<item data="20230511|216000|216500|210500|211500|17627" />
			
				<item data="20230512|210000|217000|207500|213500|24787" />
			
				<item data="20230515|213500|214000|208500|213500|13062" />
			
				<item data="20230516|216500|218000|211000|212500|15438" />
			
				<item data="20230517|212000|214000|207500|209500|26999" />
			
				<item data="20230518|211000|213500|208500|213500|21679" />
			
				<item data="20230519|215000|232000|215000|229500|93122" />
			
				<item data="20230522|229500|235000|227500|233500|34093" />
			
				<item data="20230523|233500|236000|232000|235000|16991" />
			
				<item data="20230524|233000|235000|229500|234500|14027" />
			
				<item data="20230525|238000|240500|231000|235500|28529" />
			
				<item data="20230526|236500|240000|232000|234000|36954" />
			
				<item data="20230530|238000|241000|233500|237500|30246" />
			
				<item data="20230531|237000|237000|229500|230500|24439" />
			
				<item data="20230601|228500|236000|225500|235500|13763" />
			
				<item data="20230602|236000|237500|231500|235000|18024" />
			
				<item data="20230605|234000|234000|230000|232000|16826" />
			
				<item data="20230607|232000|234000|230500|232000|16672" />
			
				<item data="20230608|231500|234000|228000|232500|22633" />
			
				<item data="20230609|234000|234000|228000|228000|34161" />
			
				<item data="20230612|230500|232500|228000|231000|15126" />
			
				<item data="20230613|232000|239000|232000|238000|33524" />
			
				<item data="20230614|238000|238500|232000|234000|24171" />
			
				<item data="20230615|234500|243000|233500|240500|32676" />
			
				<item data="20230616|241000|241000|234500|235000|18699" />
			
				<item data="20230619|236000|236000|231000|234500|16331" />
			
				<item data="20230620|235000|235000|229500|233500|14571" />
			
				<item data="20230621|233500|235500|230000|232500|15941" />
			
				<item data="20230622|233000|256000|230000|250500|105847" />
			
				<item data="20230623|250000|252000|244000|250000|43984" />
			
				<item data="20230626|252500|252500|247000|251500|24871" />
			
				<item data="20230627|250000|252000|249000|251000|22649" />
			
				<item data="20230628|252500|253000|246500|250500|19262" />
			
				<item data="20230629|250500|252000|245500|250000|28596" />
			
				<item data="20230630|250500|254500|245000|251000|33861" />
			
				<item data="20230703|254000|261500|251000|258500|41535" />
			
				<item data="20230704|255000|255500|248500|254500|37401" />
			
				<item data="20230705|258000|260000|253000|254000|27888" />
			
				<item data="20230706|252500|254000|243000|245500|31907" />
			
				<item data="20230707|244500|245000|237000|240000|32083" />
			
				<item data="20230710|238000|241000|235500|237000|16756" />
			
				<item data="20230711|239500|250500|238000|250000|31120" />
			
				<item data="20230712|250000|268500|250000|264500|103391" />
			
				<item data="20230713|268500|277000|265000|274000|111331" />
			
				<item data="20230714|275000|275500|258000|258000|82160" />
			
				<item data="20230717|264500|278500|262500|275500|75245" />
			
				<item data="20230718|280000|280000|264500|272500|59564" />
			
				<item data="20230719|272500|277000|266000|273000|42903" />
			
				<item data="20230720|270000|277000|267500|274000|31749" />
			
				<item data="20230721|267500|271500|262000|269000|44859" />
			
				<item data="20230724|268500|269000|262000|269000|24887" />
			
				<item data="20230725|270000|272000|264500|271500|39522" />
			
				<item data="20230726|273000|273500|262000|266500|55251" />
			
				<item data="20230727|270500|275500|261000|269500|44225" />
			
				<item data="20230728|270500|286500|270000|280500|65797" />
			
				<item data="20230731|282000|282500|268500|272500|50196" />
			
				<item data="20230801|273500|279500|272500|275500|37190" />
			
				<item data="20230802|275000|276000|268000|273000|32267" />
			
				<item data="20230803|270000|275000|265000|273500|40712" />
			
				<item data="20230804|271000|272500|263500|269000|26276" />
			
				<item data="20230807|264000|267500|255000|260500|40046" />
			
				<item data="20230808|266000|266000|252500|255500|37861" />
			
				<item data="20230809|255500|262000|252000|260000|22146" />
			
				<item data="20230810|258000|259000|250000|259000|26118" />
			
				<item data="20230811|256000|259000|253500|256000|12650" />
			
				<item data="20230814|252000|256000|252000|255500|14522" />
			
				<item data="20230816|256000|256000|239000|240000|42608" />
			
				<item data="20230817|240000|242500|235000|241000|26289" />
			
				<item data="20230818|235500|242500|231500|237500|34672" />
			
				<item data="20230821|240500|241500|235000|238000|23472" />
			
				<item data="20230822|240000|242500|232500|236000|30034" />
			
				<item data="20230823|232500|235500|229500|232500|30005" />
			
				<item data="20230824|238500|239500|232500|235500|15968" />
			
				<item data="20230825|230000|232500|228000|232000|26939" />
			
				<item data="20230828|234000|234000|225000|226500|30488" />
			
				<item data="20230829|228000|231000|226000|231000|27571" />
			
				<item data="20230830|233000|234000|230000|231000|17047" />
			
				<item data="20230831|232500|232500|225000|227500|34331" />
			
				<item data="20230901|228500|242000|226500|241500|58998" />
			
				<item data="20230904|242500|244500|235000|238000|28404" />
			
				<item data="20230905|237500|239000|234000|236500|11621" />
			
				<item data="20230906|235000|236500|230500|232000|21535" />
			
				<item data="20230907|229500|233000|225000|228000|49887" />
			
				<item data="20230908|229500|229500|223500|226500|18118" />
			
				<item data="20230911|229000|229000|218000|221500|33836" />
			
				<item data="20230912|223500|224500|220000|223500|19025" />
			
				<item data="20230913|223500|225500|217500|220000|37060" />
			
				<item data="20230914|221500|237500|221500|236500|50337" />
			
				<item data="20230915|237500|244000|234500|238000|33639" />
			
				<item data="20230918|233500|236500|231000|234000|26813" />
			
				<item data="20230919|233500|240000|232500|236500|20782" />
			
				<item data="20230920|236500|239000|228000|230500|22999" />
			
				<item data="20230921|229500|232500|223500|225000|24914" />
			
				<item data="20230922|220500|227000|220500|227000|21227" />
			
				<item data="20230925|230000|230500|224000|228500|12163" />
			
				<item data="20230926|228500|229000|222500|226000|9803" />
			
				<item data="20230927|225000|230500|223500|229500|10779" />
			
				<item data="20231004|224500|229000|220500|228500|21395" />
			
				<item data="20231005|232500|234500|226500|229500|20570" />
			
				<item data="20231006|232000|232000|226000|229000|10383" />
			
				<item data="20231010|231000|235000|222000|223000|29886" />
			
				<item data="20231011|239500|244500|232000|239500|78343" />
			
				<item data="20231012|241000|242500|236500|239500|28473" />
			
				<item data="20231013|238500|242000|235000|236500|27643" />
			
				<item data="20231016|233000|239000|233000|239000|27504" />
			
				<item data="20231017|240500|257000|238000|256500|64870" />
			
				<item data="20231018|252500|255000|248000|248500|31023" />
			
				<item data="20231019|242500|256000|242500|251000|42214" />
			
				<item data="20231020|246500|258000|242000|251500|45380" />
			
				<item data="20231023|252000|257500|248500|250000|29241" />
			
				<item data="20231024|254000|254000|244500|252000|44447" />
			
				<item data="20231025|252000|252000|240500|245500|48295" />
			
				<item data="20231026|237000|237500|229500|237000|44207" />
			
				<item data="20231027|242500|245500|236000|239500|27368" />
			
				<item data="20231030|241500|247000|238000|241500|16797" />
			
				<item data="20231031|244000|244500|230500|232000|28449" />
			
				<item data="20231101|235500|249000|234000|241500|31638" />
			
				<item data="20231102|247500|250000|244500|249500|27236" />
			
				<item data="20231103|247500|247500|238000|239000|37449" />
			
				<item data="20231106|244000|251500|241000|251500|44091" />
			
				<item data="20231107|251500|252000|242000|247000|39498" />
			
				<item data="20231108|247500|252000|243500|244500|26616" />
			
				<item data="20231109|246000|248000|243000|248000|13072" />
			
				<item data="20231110|245000|253000|243000|250000|31284" />
			
				<item data="20231113|252500|265500|251500|258500|77958" />
			
				<item data="20231114|260000|265000|255000|263500|42155" />
			
				<item data="20231115|266500|272500|263000|270500|64067" />
			
				<item data="20231116|270000|273000|265000|271000|26556" />
			
				<item data="20231117|270000|274500|266000|270000|28951" />
			
				<item data="20231120|268000|274500|265000|273000|17826" />
			
				<item data="20231121|275000|280000|274000|279000|39197" />
			
				<item data="20231122|276500|282000|271000|279500|28866" />
			
				<item data="20231123|278000|281000|266000|268500|44494" />
			
				<item data="20231124|268500|270500|266000|267500|16758" />
			
				<item data="20231127|265500|273500|264500|269000|18622" />
			
				<item data="20231128|270000|274500|265000|271500|22357" />
			
				<item data="20231129|270500|273500|267000|272000|18711" />
			
				<item data="20231130|270000|281000|270000|277000|65250" />
			
				<item data="20231201|277000|299500|271500|289000|96042" />
			
				<item data="20231204|288000|293000|279000|288500|41883" />
			
				<item data="20231205|285000|291000|281500|286500|48997" />
			
				<item data="20231206|288000|299000|283500|298500|57829" />
			
				<item data="20231207|295500|298500|285000|296000|39512" />
			
				<item data="20231208|300000|302500|293500|300000|47589" />
			
				<item data="20231211|303000|303000|288500|293000|41118" />
			
				<item data="20231212|297000|299500|292000|292500|21074" />
			
				<item data="20231213|291500|295000|288000|293000|19850" />
			
				<item data="20231214|296500|296500|284000|293000|55765" />
			
				<item data="20231215|293000|293000|285500|291000|30457" />
			
				<item data="20231218|291000|294500|288000|291000|20509" />
			
				<item data="20231219|289000|292500|288000|289500|16875" />
			
				<item data="20231220|290500|292000|286500|292000|21351" />
			
				<item data="20231221|288000|295500|288000|294500|28216" />
			
				<item data="20231222|297000|300500|291500|297500|31471" />
			
				<item data="20231226|299000|307500|291500|307000|42672" />
			
				<item data="20231227|305000|308500|300500|303000|25177" />
			
				<item data="20231228|301000|306000|300000|304000|29047" />
			
				<item data="20240102|301000|314000|298500|309000|32918" />
			
				<item data="20240103|302000|303000|292000|301000|38282" />
			
				<item data="20240104|298500|307500|295500|304000|23526" />
			
				<item data="20240105|308000|310500|302000|306500|25798" />
			
				<item data="20240108|306500|308000|300000|302500|23722" />
			
				<item data="20240109|306500|310000|293000|293500|43640" />
			
				<item data="20240110|293000|298000|289500|298000|26799" />
			
				<item data="20240111|298000|301500|293000|293500|21308" />
			
				<item data="20240112|296000|302500|293500|297000|26418" />
			
				<item data="20240115|297000|299500|291000|294500|16614" />
			
				<item data="20240116|294500|297500|290000|292000|17798" />
			
				<item data="20240117|293500|298000|279000|288000|23766" />
			
				<item data="20240118|290500|296000|287000|295000|12973" />
			
				<item data="20240119|299500|305000|296500|301000|27041" />
			
				<item data="20240122|310000|310500|301500|304500|48441" />
			
				<item data="20240123|306500|306500|298500|300500|18532" />
			
				<item data="20240124|300500|302500|296500|301000|12892" />
			
				<item data="20240125|300000|304000|296000|303500|22451" />
			
				<item data="20240126|301000|303000|283000|283500|64621" />
			
				<item data="20240129|283000|286000|268000|272500|56613" />
			
				<item data="20240130|273000|278000|265000|274000|35094" />
			
				<item data="20240131|271500|273000|267500|270500|20229" />
			
				<item data="20240201|268500|274000|264000|270000|45214" />
			
				<item data="20240202|273500|283000|271000|276000|43262" />
			
				<item data="20240205|273500|275500|262000|266000|32900" />
			
				<item data="20240206|267000|279000|265000|276500|35105" />
			
				<item data="20240207|275500|277500|272000|272500|18493" />
			
				<item data="20240208|275500|278500|268000|271000|29643" />
			
				<item data="20240213|273000|279000|266500|274500|66880" />
			
				<item data="20240214|272500|289000|266000|288000|53352" />
			
				<item data="20240215|288000|290500|281000|287500|30089" />
			
				<item data="20240216|285000|290500|281000|285500|35246" />
			
				<item data="20240219|284000|284000|272000|275000|37545" />
			
				<item data="20240220|275000|281000|270500|276500|35583" />
			
				<item data="20240221|273500|280000|271500|277500|28826" />
			
				<item data="20240222|281000|285000|277000|278000|30060" />
			
				<item data="20240223|280500|280500|270500|273500|30115" />
			
				<item data="20240226|272500|274500|267000|267500|26883" />
			
				<item data="20240227|267500|272500|263000|263000|28267" />
			
				<item data="20240228|263500|272500|262500|267500|38487" />
			
				<item data="20240229|267500|273500|263000|272000|27219" />
			
				<item data="20240304|280000|280000|272000|276000|61712" />
			
				<item data="20240305|274500|279500|273000|277500|26830" />
			
				<item data="20240306|274000|287000|272000|286000|35422" />
			
				<item data="20240307|283000|283500|274500|278500|52469" />
			
				<item data="20240308|281000|282500|273000|278000|37178" />
			
				<item data="20240311|271000|279500|270500|279500|23583" />
			
				<item data="20240312|278500|285500|275500|284500|34196" />
			
				<item data="20240313|284500|296000|281500|288000|51556" />
			
				<item data="20240314|288000|297500|285500|295000|41831" />
			
				<item data="20240315|288500|291500|282500|287500|30456" />
			
				<item data="20240318|287500|295000|287000|295000|24336" />
			
				<item data="20240319|292000|292000|282000|283500|24944" />
			
				<item data="20240320|284500|304500|280000|303500|78176" />
			
				<item data="20240321|310500|322000|306000|313500|99860" />
			
				<item data="20240322|318500|318500|302000|305000|36934" />
			
				<item data="20240325|304000|307000|296500|296500|23174" />
			
				<item data="20240326|299000|308000|291000|294500|50484" />
			
				<item data="20240327|294500|297500|290500|293500|38310" />
			
				<item data="20240328|293000|296000|288500|292500|50648" />
			
				<item data="20240329|295000|318500|293000|312500|95166" />
			
				<item data="20240401|315000|316500|309000|313500|30008" />
			
				<item data="20240402|312000|315500|306000|312000|43328" />
			
				<item data="20240403|306500|312500|303500|310000|36699" />
			
				<item data="20240404|310500|318500|309500|312000|50146" />
			
				<item data="20240405|305000|317500|304500|314500|31635" />
			
				<item data="20240408|316000|321000|307000|308500|31199" />
			
				<item data="20240409|306500|311000|295500|297000|34361" />
			
				<item data="20240411|292500|298000|289000|291000|61258" />
			
				<item data="20240412|297500|310000|294500|298500|56050" />
			
				<item data="20240415|293000|300500|292000|298500|24907" />
			
				<item data="20240416|293500|299000|290000|295000|28481" />
			
				<item data="20240417|302000|309500|298500|303000|52528" />
			
				<item data="20240418|301000|305500|289000|302000|26488" />
			
				<item data="20240419|297000|299000|287500|297500|41431" />
			
				<item data="20240422|293000|300000|279500|288000|55148" />
			
				<item data="20240423|291000|292500|283000|283000|18799" />
			
				<item data="20240424|290000|297000|289000|291500|26670" />
			
				<item data="20240425|287500|290500|285000|288500|17581" />
			
				<item data="20240426|293500|298000|291500|297000|23393" />
			
				<item data="20240429|299500|312000|295500|312000|43321" />
			
				<item data="20240430|312000|312500|301000|302000|26744" />
			
				<item data="20240502|301500|312000|301500|309500|26472" />
			
				<item data="20240503|313500|316500|306000|309000|17060" />
			
				<item data="20240507|319500|320000|312000|315000|42773" />
			
				<item data="20240508|312000|315000|309000|312500|11689" />
			
				<item data="20240509|310500|313000|309000|311000|12715" />
			
				<item data="20240510|311000|312000|301500|309000|16519" />
			
				<item data="20240513|312000|312000|293000|296000|32059" />
			
				<item data="20240514|297000|298500|293000|296500|14007" />
			
				<item data="20240516|301500|305500|296500|298000|14463" />
			
				<item data="20240517|306000|314500|304000|304000|45715" />
			
				<item data="20240520|307500|313500|301000|312500|29275" />
			
				<item data="20240521|315500|325500|311500|324500|40855" />
			
				<item data="20240522|327500|327500|316500|321500|21489" />
			
				<item data="20240523|325500|328000|314500|317500|23556" />
			
				<item data="20240524|312000|313000|302000|304000|24942" />
			
				<item data="20240527|307000|312000|302500|308500|18178" />
			
				<item data="20240528|319000|358500|317000|343500|167248" />
			
				<item data="20240529|343000|343000|329500|330500|44172" />
			
				<item data="20240530|330500|330500|317500|325500|30780" />
			
				<item data="20240531|325000|332500|323500|329500|26883" />
			
				<item data="20240603|329000|333000|319000|322500|43834" />
			
				<item data="20240604|322500|325000|307500|313500|50479" />
			
				<item data="20240605|317000|319500|309500|313000|26203" />
			
				<item data="20240607|319500|322000|312000|312500|23793" />
			
				<item data="20240610|310500|319500|310000|315000|23071" />
			
				<item data="20240611|312500|321000|310500|313000|19896" />
			
				<item data="20240612|313000|319000|313000|315000|13711" />
			
				<item data="20240613|317500|318500|307500|308000|59809" />
			
				<item data="20240614|308000|311500|301500|305000|35526" />
			
				<item data="20240617|304000|308000|300000|303000|20936" />
			
				<item data="20240618|305000|310500|304500|308500|40554" />
			
				<item data="20240619|312000|317500|307000|315500|50093" />
			
				<item data="20240620|319000|326000|309000|313000|32927" />
			
				<item data="20240621|310500|310500|298000|301000|50294" />
			
				<item data="20240624|298500|299000|291500|296000|30447" />
			
				<item data="20240625|291000|293500|281500|290000|54202" />
			
				<item data="20240626|290500|291500|286500|291000|27114" />
			
				<item data="20240627|289500|293500|286500|291500|14872" />
			
				<item data="20240628|292000|292000|285500|290500|18470" />
			
				<item data="20240701|290500|296500|287500|294500|20206" />
			
				<item data="20240702|292000|295500|285500|287500|24570" />
			
				<item data="20240703|285000|287000|276500|280500|35532" />
			
				<item data="20240704|284500|297000|284500|295500|50543" />
			
				<item data="20240705|303000|305500|297000|300000|40595" />
			
				<item data="20240708|303000|303500|294500|297000|24141" />
			
				<item data="20240709|298500|299500|293000|293500|25125" />
			
				<item data="20240710|293500|294000|285000|290000|29408" />
			
				<item data="20240711|294500|295000|286000|287000|30439" />
			
				<item data="20240712|284500|288500|283000|288000|23644" />
			
				<item data="20240715|288000|293000|284500|293000|25117" />
			
				<item data="20240716|291000|291500|283000|284500|28163" />
			
				<item data="20240717|286500|286500|276500|280500|36381" />
			
				<item data="20240718|274500|281000|268000|281000|50727" />
			
				<item data="20240719|277500|284000|275000|281000|19008" />
			
				<item data="20240722|278500|281000|271500|275000|17592" />
			
				<item data="20240723|278000|282500|263500|264500|36921" />
			
				<item data="20240724|263500|263500|257000|259500|26855" />
			
				<item data="20240725|255000|259500|252000|255000|42266" />
			
				<item data="20240726|256500|263000|254500|258000|23213" />
			
				<item data="20240729|261000|261000|249500|254000|27649" />
			
				<item data="20240730|250500|255000|248000|251500|17548" />
			
				<item data="20240731|253000|266000|250500|263500|30892" />
			
				<item data="20240801|270500|271000|259500|262500|26226" />
			
				<item data="20240802|259000|259000|248500|251500|29106" />
			
				<item data="20240805|247000|247500|221000|222500|73789" />
			
				<item data="20240806|234500|241000|229000|237500|34789" />
			
				<item data="20240807|235500|244500|233500|238000|23395" />
			
				<item data="20240808|231000|237000|230000|234000|14544" />
			
				<item data="20240809|241000|244500|239000|242500|17021" />
			
				<item data="20240812|240000|246500|240000|245500|10092" />
			
				<item data="20240813|243500|247500|240500|243000|7798" />
			
				<item data="20240814|247000|250500|245500|249500|10607" />
			
				<item data="20240816|256500|258500|253500|256500|16761" />
			
				<item data="20240819|254000|258500|250500|254000|18940" />
			
				<item data="20240820|256500|259000|252500|256000|22841" />
			
				<item data="20240821|251000|256000|250500|253500|8345" />
			
				<item data="20240822|254000|254500|245000|246500|15433" />
			
				<item data="20240823|243500|245500|241000|244500|8911" />
			
				<item data="20240826|244500|245000|235000|236000|11986" />
			
				<item data="20240827|234500|235000|230000|232000|13905" />
			
				<item data="20240828|232000|236500|230000|236000|13268" />
			
				<item data="20240829|229500|231500|226000|227000|21555" />
			
				<item data="20240830|227000|239000|226000|237000|18900" />
			
				<item data="20240902|237000|238500|231500|234000|10151" />
			
				<item data="20240903|235000|235000|229500|229500|6868" />
			
				<item data="20240904|221000|227500|219500|221000|20138" />
			
				<item data="20240905|221000|224500|215000|216500|20493" />
			
				<item data="20240906|216500|218000|211500|215500|18065" />
			
				<item data="20240909|211500|221500|210500|219000|10493" />
			
				<item data="20240910|220000|229000|214500|216500|10359" />
			
				<item data="20240911|215000|223000|214500|218500|11653" />
			
				<item data="20240912|224500|228000|219500|221000|29216" />
			
				<item data="20240913|219000|219500|210000|212500|35487" />
			
				<item data="20240919|213000|216500|208000|216500|35345" />
			
				<item data="20240920|219500|219500|209000|210000|30295" />
			
				<item data="20240923|209500|217500|209500|214500|17915" />
			
				<item data="20240924|215500|220000|215500|220000|17002" />
			
				<item data="20240925|223500|231500|221500|224500|29112" />
			
				<item data="20240926|230000|234000|227500|230500|21351" />
			
				<item data="20240927|228000|230500|225000|226000|20910" />
			
				<item data="20240930|228000|229500|222000|222000|18120" />
			
				<item data="20241002|220000|230500|215500|226500|21021" />
			
				<item data="20241004|228500|230000|223000|223500|11959" />
			
				<item data="20241007|223500|229500|221500|224000|13308" />
			
				<item data="20241008|221500|225000|215000|215000|16918" />
			
				<item data="20241010|216000|218500|211500|212500|14520" />
			
				<item data="20241011|214500|217500|212500|216000|18658" />
			
				<item data="20241014|216000|220000|213500|216500|12980" />
			
				<item data="20241015|219500|220500|212500|214000|14476" />
			
				<item data="20241016|210000|212000|202000|202000|38799" />
			
				<item data="20241017|204500|211000|203000|205500|33640" />
			
				<item data="20241018|207500|207500|200000|203000|33464" />
			
				<item data="20241021|204000|206000|200000|205500|14484" />
			
				<item data="20241022|205500|206000|196500|196600|22913" />
			
				<item data="20241023|198000|201500|194000|199600|25747" />
			
				<item data="20241024|198600|198600|194700|195200|25700" />
			
				<item data="20241025|197100|199000|192900|195000|21718" />
			
				<item data="20241028|196600|200500|195100|199900|11296" />
			
				<item data="20241029|197600|197900|193800|197000|16501" />
			
				<item data="20241030|197600|198100|193900|195000|15051" />
			
				<item data="20241031|193600|204000|191400|204000|29809" />
			
				<item data="20241101|200500|202000|195900|196200|18195" />
			
				<item data="20241104|197700|204000|195700|202000|25861" />
			
				<item data="20241105|202500|203000|199600|203000|10868" />
			
				<item data="20241106|204000|210000|202000|204500|23987" />
			
				<item data="20241107|202000|203500|198300|199600|17015" />
			
				<item data="20241108|205000|206000|198100|198300|10895" />
			
				<item data="20241111|195500|198300|190100|191200|18610" />
			
				<item data="20241112|191200|193700|186300|188800|25287" />
			
				<item data="20241113|186400|189900|184000|187800|19032" />
			
				<item data="20241114|188700|191500|186000|187100|20486" />
			
				<item data="20241115|184600|191300|182000|191300|22229" />
			
				<item data="20241118|191300|191600|184200|186600|24636" />
			
				<item data="20241119|186600|190700|185500|187700|16361" />
			
				<item data="20241120|187700|190600|187100|189500|10691" />
			
				<item data="20241121|189100|194200|188600|190800|12820" />
			
				<item data="20241122|190900|194900|190800|193500|16538" />
			
				<item data="20241125|192600|197900|191400|197200|12286" />
			
				<item data="20241126|195400|197300|193200|193800|10596" />
			
				<item data="20241127|195400|195400|189400|191500|22996" />
			
				<item data="20241128|192800|192800|185600|185600|14196" />
			
				<item data="20241129|188000|188000|178900|179500|24218" />
			
				<item data="20241202|181300|181400|172500|174000|45380" />
			
				<item data="20241203|172900|174900|171100|172400|32395" />
			
				<item data="20241204|169400|170100|166400|168500|31953" />
			
				<item data="20241205|167000|170900|165800|168200|22733" />
			
				<item data="20241206|168200|169600|164800|168100|24539" />
			
				<item data="20241209|166900|166900|159600|159600|28780" />
			
				<item data="20241210|162500|168500|161600|167900|20799" />
			
				<item data="20241211|167300|174800|166000|171800|25448" />
			
				<item data="20241212|174500|180400|172600|177400|35186" />
			
				<item data="20241213|179100|181100|176900|177900|20431" />
			
				<item data="20241216|177900|185500|177900|179700|24175" />
			
				<item data="20241217|181000|181100|170800|172800|24279" />
			
				<item data="20241218|174200|174200|169000|172400|33712" />
			
				<item data="20241219|169000|171300|166700|167300|18784" />
			
				<item data="20241220|167000|168300|165200|165600|15002" />
			
				<item data="20241223|168400|169500|166500|169200|13833" />
			
				<item data="20241224|168100|169800|166900|169700|11674" />
			
				<item data="20241226|168300|169200|163200|163400|16879" />
			
				<item data="20241227|163600|166300|161200|164200|15816" />
			
				<item data="20241230|164200|168000|161500|165400|14345" />
			
				<item data="20250102|162100|164500|160100|163000|14306" />
			
				<item data="20250103|162300|172200|162300|170500|20315" />
			
				<item data="20250106|171000|181500|170200|179300|30911" />
			
				<item data="20250107|183700|183700|173500|173500|29354" />
			
				<item data="20250108|173500|184000|173500|181700|24154" />
			
				<item data="20250109|181100|182500|177200|177900|16386" />
			
				<item data="20250110|177100|179200|174300|174300|19446" />
			
				<item data="20250113|172400|178700|172200|175000|14528" />
			
				<item data="20250114|177500|179500|174000|178500|12618" />
			
				<item data="20250115|182400|182800|173500|174500|49402" />
			
				<item data="20250116|176900|179200|175700|178100|31300" />
			
				<item data="20250117|177600|183800|176800|181300|36994" />
			
				<item data="20250120|184000|185400|181300|184100|29134" />
			
				<item data="20250121|187700|188000|180600|182700|23685" />
			
				<item data="20250122|183000|184600|179400|183000|19216" />
			
				<item data="20250123|184000|184000|172500|173900|40797" />
			
				<item data="20250124|174800|177300|172800|175900|13154" />
			
				<item data="20250131|174900|174900|164500|168800|14919" />
			
				<item data="20250203|164300|166000|160600|162700|25304" />
			
				<item data="20250204|166500|168200|162800|163500|17102" />
			
				<item data="20250205|166000|170300|165500|169000|10309" />
			
				<item data="20250206|169500|171000|165900|168800|20561" />
			
				<item data="20250207|174700|182700|172900|178200|70402" />
			
				<item data="20250210|177300|188300|171500|188100|56876" />
			
				<item data="20250211|191700|196000|183600|192000|69086" />
			
				<item data="20250212|191100|194300|187000|189000|21742" />
			
				<item data="20250213|191900|192400|179200|184600|65327" />
			
				<item data="20250214|186300|193000|184500|188200|34959" />
			
				<item data="20250217|189800|191700|186500|189700|24629" />
			
				<item data="20250218|189700|199200|188500|197900|43650" />
			
				<item data="20250219|201000|205500|199400|204000|71097" />
			
				<item data="20250220|204500|205000|197800|198100|48906" />
			
				<item data="20250221|198100|200500|196100|198300|34034" />
			
				<item data="20250224|193700|197900|192700|195900|17590" />
			
				<item data="20250225|193200|204500|192100|199200|37210" />
			
				<item data="20250226|200500|201500|193800|194600|21931" />
			
				<item data="20250227|195200|197200|193000|193800|13657" />
			
				<item data="20250228|187400|191500|184500|186000|31179" />
			
				<item data="20250304|185100|186800|181900|184000|13412" />
			
				<item data="20250305|186700|192000|185000|189000|18584" />
			
				<item data="20250306|191300|191300|180900|182300|20851" />
			
				<item data="20250307|181300|194800|180200|193700|28061" />
			
				<item data="20250310|194500|203000|193800|199300|38436" />
			
				<item data="20250311|195000|202000|191300|199400|29297" />
			
				<item data="20250312|200500|205000|198300|202500|35551" />
			
				<item data="20250313|205000|211000|199900|200000|58872" />
			
				<item data="20250314|202000|214000|200000|210000|62914" />
			
				<item data="20250317|216000|216500|206000|207500|33493" />
			
				<item data="20250318|211000|213000|200500|201000|30193" />
			
				<item data="20250319|200500|209500|199400|204500|30104" />
			
				<item data="20250320|207000|207000|201500|205000|20750" />
			
				<item data="20250321|207500|212000|204000|206500|42506" />
			
				<item data="20250324|204500|206000|201000|201500|13007" />
			
				<item data="20250325|204500|205000|199300|201000|16808" />
			
				<item data="20250326|201000|204500|200500|202500|8993" />
			
				<item data="20250327|200000|203000|198700|198700|7082" />
			
				<item data="20250328|197400|198000|191300|192600|23570" />
			
				<item data="20250331|185000|192400|185000|188600|17345" />
			
				<item data="20250401|190700|195600|188000|195000|19642" />
			
				<item data="20250402|196300|196900|191000|193000|6922" />
			
				<item data="20250403|184200|191700|183700|185100|17216" />
			
				<item data="20250404|184100|185100|170500|174300|34709" />
			
				<item data="20250407|165100|169600|164000|165600|19852" />
			
				<item data="20250408|170300|174700|165800|167000|14733" />
			
				<item data="20250409|169700|169700|159000|161200|19369" />
			
				<item data="20250410|173200|176000|169100|175400|21223" />
			
				<item data="20250411|171900|178000|167500|176400|23273" />
			
				<item data="20250414|176700|179700|174200|174400|12856" />
			
				<item data="20250415|173500|179900|173500|177500|10571" />
			
				<item data="20250416|177000|178500|172300|173000|22771" />
			
				<item data="20250417|173300|180300|171000|178000|21015" />
			
				<item data="20250418|175500|177500|172100|175000|27502" />
			
				<item data="20250421|173900|178200|173900|175800|23976" />
			
				<item data="20250422|177000|178300|174800|176700|19744" />
			
				<item data="20250423|180000|180300|178300|178800|13971" />
			
				<item data="20250424|177400|180800|173700|175000|28593" />
			
				<item data="20250425|177200|179500|176500|178900|14101" />
			
				<item data="20250428|178800|178900|171800|172800|21887" />
			
				<item data="20250429|172900|176700|170500|175800|23531" />
			
				<item data="20250430|174100|175900|173100|174000|18858" />
			
				<item data="20250502|174000|179400|172400|178000|24319" />
			
				<item data="20250507|180000|180900|174900|175600|17450" />
			
				<item data="20250508|177300|180300|174700|174900|19996" />
			
				<item data="20250509|175400|175400|172800|173800|10521" />
			
				<item data="20250512|177800|182600|174500|182600|31862" />
			
				<item data="20250513|184200|185400|182400|182600|17922" />
			
				<item data="20250514|184000|189300|183700|187000|30610" />
			
				<item data="20250515|184600|189500|179200|179800|21782" />
			
				<item data="20250516|181400|181400|175300|177900|16061" />
			
				<item data="20250519|175100|176200|168500|169700|30805" />
			
				<item data="20250520|172700|172700|164900|166200|31775" />
			
				<item data="20250521|166300|168100|165900|166000|9750" />
			
				<item data="20250522|166000|166000|161000|161600|22436" />
			
				<item data="20250523|163200|163200|158400|159300|20918" />
			
				<item data="20250526|159800|162000|157100|157900|21979" />
			
				<item data="20250527|157500|157900|155000|156000|19238" />
			
				<item data="20250528|157100|160000|156200|160000|22808" />
			
				<item data="20250529|161800|162100|159000|161600|16642" />
			
				<item data="20250530|160300|162700|158800|159600|20048" />
			
				<item data="20250602|158800|162600|158800|161200|20533" />
			
				<item data="20250604|164300|165800|163000|164000|19442" />
			
				<item data="20250605|163600|168800|162400|166700|28426" />
			
				<item data="20250609|166900|168800|166000|166600|15046" />
			
				<item data="20250610|167100|170000|166200|168700|14496" />
			
				<item data="20250611|169100|172800|169100|171900|26108" />
			
				<item data="20250612|171000|172900|169400|169400|22234" />
			
				<item data="20250613|169200|172900|164500|167000|32545" />
			
				<item data="20250616|167000|167800|162100|166200|12018" />
			
				<item data="20250617|166100|172800|165000|167800|21879" />
			
				<item data="20250618|166200|171900|166200|170800|13232" />
			
				<item data="20250619|171200|171500|168400|169300|11811" />
			
				<item data="20250620|169300|184600|168000|183900|64624" />
			
				<item data="20250623|179000|181900|172300|176100|32933" />
			
				<item data="20250624|179800|183000|178600|179900|25929" />
			
				<item data="20250625|182200|185500|178800|182000|26961" />
			
				<item data="20250626|184100|184400|178600|179300|14867" />
			
				<item data="20250627|180200|181100|176000|178000|14178" />
			
				<item data="20250630|179700|184000|177700|180000|19712" />
			
				<item data="20250701|179100|182300|179000|180800|19821" />
			
				<item data="20250702|182000|182200|179100|182000|14960" />
			
				<item data="20250703|183900|188400|182000|187600|20964" />
			
				<item data="20250704|189900|190000|184500|184800|16230" />
			
				<item data="20250707|184800|187200|182200|183300|9753" />
			
				<item data="20250708|181500|182500|178100|179300|22693" />
			
				<item data="20250709|179000|180300|176000|177300|15266" />
			
				<item data="20250710|179300|181300|178500|179800|10966" />
			
				<item data="20250711|180100|196900|180100|194700|60662" />
			
				<item data="20250714|191700|198400|190100|192100|28266" />
			
				<item data="20250715|190800|197400|188500|197000|41366" />
			
				<item data="20250716|202500|215500|200000|211500|105115" />
			
				<item data="20250717|209000|215000|206000|214000|50206" />
			
				<item data="20250718|216500|216500|210000|210500|26471" />
			
				<item data="20250721|210500|216000|209000|212000|15327" />
			
				<item data="20250722|216000|216000|208000|211500|19239" />
			
				<item data="20250723|210000|211500|205000|208500|18984" />
			
				<item data="20250724|208500|211000|203500|205500|18257" />
			
				<item data="20250725|201500|205000|200500|201000|11333" />
			
				<item data="20250728|211500|238500|210000|232500|187419" />
			
				<item data="20250729|249000|249000|234000|245500|146282" />
			
				<item data="20250730|243000|255000|241500|248500|87068" />
			
				<item data="20250731|246500|247000|234000|237500|74976" />
			
				<item data="20250801|229000|235500|218000|220000|92600" />
			
				<item data="20250804|222500|223500|218000|219000|21126" />
			
				<item data="20250805|224500|225500|220500|222500|27961" />
			
				<item data="20250806|219500|222500|216000|220500|22970" />
			
				<item data="20250807|243000|243000|229000|233500|63859" />
			
				<item data="20250808|238500|240500|230000|231000|37793" />
			
				<item data="20250811|234000|238000|231500|233500|31850" />
			
				<item data="20250812|236500|242500|234500|234500|61798" />
			
				<item data="20250813|243000|246500|240500|243000|62806" />
			
				<item data="20250814|239000|247500|236500|243000|32781" />
			
				<item data="20250818|234500|235500|228000|229000|53225" />
			
				<item data="20250819|234000|234000|228000|229000|30257" />
			
				<item data="20250820|221000|225500|218000|224000|30700" />
			
				<item data="20250821|227000|229000|222000|223500|27952" />
			
				<item data="20250822|223500|224500|218000|221500|27629" />
			
				<item data="20250825|226000|226000|219000|220500|30876" />
			
				<item data="20250826|219000|222000|218000|218000|30711" />
			
				<item data="20250827|219500|219500|211500|215000|42434" />
			
				<item data="20250828|212000|213500|205000|207500|63803" />
			
				<item data="20250829|211000|220500|208000|218500|60605" />
			
				<item data="20250901|212000|213500|206000|207000|25698" />
			
				<item data="20250902|209000|209500|202500|204000|24665" />
			
				<item data="20250903|202000|205000|200000|202000|22764" />
			
				<item data="20250904|204500|205000|201000|202500|25001" />
			
				<item data="20250905|206000|208000|203500|205000|18279" />
			
				<item data="20250908|208000|209000|205500|207500|19603" />
			
				<item data="20250909|208500|217000|208000|216000|38310" />
			
				<item data="20250910|222000|235000|219000|229000|99089" />
			
				<item data="20250911|230500|235000|227000|232500|45519" />
			
				<item data="20250912|242000|248000|238000|242000|92161" />
			
				<item data="20250915|257000|263500|252000|260500|124653" />
			
				<item data="20250916|263000|269500|255500|267000|70025" />
			
				<item data="20250917|260500|275500|258000|273500|63898" />
			
				<item data="20250918|273000|295000|267500|281500|89149" />
			
				<item data="20250919|283000|287000|275000|282500|47787" />
			
				<item data="20250922|284500|289500|279500|286500|37578" />
			
				<item data="20250923|289500|290000|275000|283500|52917" />
			
				<item data="20250924|278000|290000|277500|289000|47268" />
			
				<item data="20250925|284000|305000|282500|293000|59904" />
			
				<item data="20250926|285000|291500|282000|286500|53253" />
			
				<item data="20250929|286500|294000|284000|288000|23917" />
			
				<item data="20250930|288000|297500|285000|288500|16410" />
			
				<item data="20251001|289500|298000|288000|291000|32249" />
			
				<item data="20251002|297500|300500|287500|287500|78960" />
			
				<item data="20251010|297000|299000|273000|288500|51502" />
			
				<item data="20251013|284000|292500|276500|291500|42858" />
			
				<item data="20251014|298000|300000|272000|283500|61409" />
			
				<item data="20251015|284500|293500|283000|288500|45778" />
			
				<item data="20251016|289500|291000|283000|288000|25267" />
			
				<item data="20251017|282500|290000|281500|282500|36389" />
			
				<item data="20251020|280000|284000|273500|278500|43982" />
			
				<item data="20251021|281500|284000|271000|280500|35399" />
			
				<item data="20251022|274500|276500|263500|276500|66132" />
			
				<item data="20251023|268000|279500|268000|273500|46380" />
			
				<item data="20251024|278500|280500|272000|276000|40545" />
			
				<item data="20251027|279000|279000|270500|275000|36746" />
			
				<item data="20251028|273000|287000|272000|277500|51908" />
			
				<item data="20251029|282500|292000|277500|291500|51006" />
			
				<item data="20251030|291500|291500|276000|285000|54049" />
			
				<item data="20251031|279500|288000|279500|283000|25365" />
			
				<item data="20251103|282000|285000|278000|283000|35995" />
			
				<item data="20251104|285500|291000|278000|282500|45767" />
			
				<item data="20251105|276500|281500|259000|271000|58082" />
			
				<item data="20251106|274000|276000|264500|268000|59065" />
			
				<item data="20251107|264000|268000|253000|259000|46576" />
			
				<item data="20251110|262000|269000|257500|268500|35500" />
			
				<item data="20251111|277000|285000|275000|281000|49586" />
			
				<item data="20251112|279000|279500|273000|275000|35756" />
			
				<item data="20251113|275000|279500|272500|277500|26656" />
			
				<item data="20251114|272000|272000|264000|268000|51141" />
			
				<item data="20251117|271000|272500|263000|270500|24725" />
			
				<item data="20251118|266000|267500|249500|251000|47613" />
			
				<item data="20251119|250000|250000|240000|244000|31494" />
			
				<item data="20251120|254500|255500|247500|248500|15107" />
			
				<item data="20251121|234000|237500|228000|230000|50733" />
			
				<item data="20251124|232500|235000|229000|229500|19762" />
			
				<item data="20251125|239000|247000|234500|245000|44296" />
			
				<item data="20251126|247000|249000|240500|248000|21896" />
			
				<item data="20251127|251500|253000|246000|247000|15480" />
			
				<item data="20251128|253000|264000|248500|262000|48143" />
			
				<item data="20251201|271000|298000|270000|295500|125619" />
			
				<item data="20251202|293000|294000|280500|284500|47692" />
			
				<item data="20251203|289500|293000|281500|285000|29722" />
			
				<item data="20251204|282000|284500|269500|273500|55869" />
			
				<item data="20251205|274000|275000|268500|271500|21273" />
			
				<item data="20251208|275500|286000|269000|273500|27653" />
			
				<item data="20251209|277000|278000|272000|275000|28025" />
			
				<item data="20251210|273000|276000|264000|267000|32788" />
			
				<item data="20251211|269000|270000|262000|262500|30677" />
			
				<item data="20251212|263000|265500|259500|264000|36310" />
			
				<item data="20251215|260000|260000|241500|256000|22399" />
			
				<item data="20251216|253500|255500|248000|248500|22039" />
			
				<item data="20251217|249500|262500|249500|260500|22152" />
			
				<item data="20251218|260000|260500|251500|253500|16684" />
			
				<item data="20251219|254500|262000|251000|256500|21476" />
			
				<item data="20251222|263000|265500|259500|264000|23342" />
			
				<item data="20251223|267500|271000|261500|265500|25410" />
			
				<item data="20251224|267000|269000|257500|258000|20325" />
			
				<item data="20251226|260500|262000|255000|260500|37703" />
			
				<item data="20251229|261000|263500|254000|256500|41436" />
			
				<item data="20251230|255500|264500|254000|262000|30900" />
			
				<item data="20260102|262000|281000|260000|279000|54072" />
			
				<item data="20260105|284000|290000|276000|282500|58948" />
			
				<item data="20260106|280000|284000|268500|280000|60544" />
			
				<item data="20260107|287500|309500|284000|293000|80595" />
			
				<item data="20260108|287000|297500|283000|283500|52658" />
			
				<item data="20260109|283000|288500|279500|283500|42169" />
			
				<item data="20260112|287000|292500|270000|277000|50356" />
			
				<item data="20260113|277500|283000|273000|278000|36061" />
			
				<item data="20260114|278500|283000|275500|283000|29474" />
			
				<item data="20260115|284000|295000|279000|287500|36136" />
			
				<item data="20260116|289000|294500|283500|292000|43229" />
			
				<item data="20260119|290500|309500|290500|305000|59247" />
			
				<item data="20260120|307500|317500|297500|309500|56856" />
			
				<item data="20260121|298000|343000|295500|339500|110483" />
			
				<item data="20260122|336500|343000|319000|325000|80640" />
			
				<item data="20260123|328000|330000|318500|330000|49657" />
			
				<item data="20260126|335000|339000|323500|337000|112842" />
			
				<item data="20260127|350000|368500|332000|361000|128090" />
			
				<item data="20260128|366000|415000|352500|412500|172669" />
			
				<item data="20260129|440500|453500|392000|450000|134199" />
			
				<item data="20260130|454000|530000|445000|488500|189127" />
			
				<item data="20260202|455500|463000|415500|419500|132225" />
			
				<item data="20260203|444500|445500|419500|441000|91245" />
			
				<item data="20260204|432500|437500|420000|421500|77608" />
			
				<item data="20260205|413000|422500|400000|411000|77377" />
			
				<item data="20260206|409500|418000|382500|407000|61448" />
			
				<item data="20260209|419000|432000|414500|429000|64660" />
			
				<item data="20260210|432500|434500|405000|409000|43025" />
			
				<item data="20260211|412500|413000|394000|394000|50041" />
			
				<item data="20260212|394000|402000|390000|397500|45965" />
			
				<item data="20260213|390000|403000|390000|398000|41466" />
			
				<item data="20260219|402000|425000|400000|420500|94279" />
			
				<item data="20260220|418500|423000|407000|417500|50272" />
			
				<item data="20260223|414000|422500|403500|410500|62110" />
			
				<item data="20260224|405500|413000|398500|410500|44946" />
			
				<item data="20260225|406500|415500|394500|404500|35419" />
			
				<item data="20260226|407000|443000|400500|441000|95497" />
			
	


	</chartdata>
</protocol>
